MyConnect/AuthLogin.py
MyConnect/main.py
MyConnect/moduleTest.py
MyConnect/root.py
MyConnect/user.py
MyConnect/venv/Scripts/activate_this.py
MyConnect_SQL-1.1.0.dist-info/METADATA
MyConnect_SQL-1.1.0.dist-info/WHEEL
MyConnect_SQL-1.1.0.dist-info/top_level.txt
MyConnect_SQL-1.1.0.dist-info/RECORD
