Metadata-Version: 2.1
Name: MyConnect - SQL
Version: 1.1.0
Summary: Auth Login simplifies the creation of login page and account creation.
Home-page: https://github.com/Rayanis55/AuthLogin
Author: Venorix - Rayanis55
License: MIT
Requires-Python: >=3.0
